ovito_stride/__init__.py
ovito_stride-0.0.0.dist-info/METADATA
ovito_stride-0.0.0.dist-info/WHEEL
ovito_stride-0.0.0.dist-info/licenses/LICENSE
ovito_stride-0.0.0.dist-info/RECORD
