Metadata-Version: 2.4
Name: ovito-stride
Version: 0.0.0
Summary: STRIDE plugin for OVITO
Project-URL: Homepage, https://github.com/lonelyneutrin0/ovito-stride
Author-email: Hrishikesh Belagali <belagal1@msu.edu>
License-Expression: MIT
License-File: LICENSE
Keywords: OVITO,STRIDE,molecular dynamics
Classifier: Programming Language :: Python :: 3.9
Classifier: Programming Language :: Python :: 3.10
Classifier: Programming Language :: Python :: 3.11
Classifier: Programming Language :: Python :: 3.12
Requires-Python: >=3.9
Requires-Dist: ovito~=3.12.0
Provides-Extra: dev
Requires-Dist: hatchling~=1.27.0; extra == 'dev'
Requires-Dist: mypy~=1.13.0; extra == 'dev'
Requires-Dist: pdoc~=15.0.4; extra == 'dev'
Requires-Dist: pytest~=8.0.2; extra == 'dev'
Requires-Dist: ruff~=0.9.4; extra == 'dev'
